beehiiv_python_client/__init__.py
beehiiv_python_client/client.py
beehiiv_python_client/exceptions.py
beehiiv_python_client/models.py
beehiiv_python_client/resources/__init__.py
beehiiv_python_client/resources/automations.py
beehiiv_python_client/resources/base.py
beehiiv_python_client/resources/custom_fields.py
beehiiv_python_client/resources/posts.py
beehiiv_python_client/resources/publications.py
beehiiv_python_client/resources/segments.py
beehiiv_python_client/resources/subscriptions.py
beehiiv_python_client/resources/tiers.py
beehiiv_python_client-0.1.3.dist-info/LICENSE
beehiiv_python_client-0.1.3.dist-info/METADATA
beehiiv_python_client-0.1.3.dist-info/WHEEL
beehiiv_python_client-0.1.3.dist-info/RECORD
