Metadata-Version: 2.3
Name: beehiiv-python-client
Version: 0.1.3
Summary: A Python client for the Beehiiv API v2.
License: MIT
Keywords: beehiiv,api,client,newsletter
Author: Salah El. Elnabrawy
Author-email: salah.nb.03@gmail.com
Requires-Python: >=3.8.1,<4.0.0
Classifier: Development Status :: 3 - Alpha
Classifier: Intended Audience :: Developers
Classifier: License :: OSI Approved :: MIT License
Classifier: Operating System :: OS Independent
Classifier: Programming Language :: Python :: 3
Classifier: Programming Language :: Python :: 3.9
Classifier: Programming Language :: Python :: 3.10
Classifier: Programming Language :: Python :: 3.11
Classifier: Programming Language :: Python :: 3.12
Classifier: Programming Language :: Python :: 3.13
Classifier: Programming Language :: Python :: 3.8
Classifier: Topic :: Communications :: Email
Classifier: Topic :: Software Development :: Libraries :: Python Modules
Requires-Dist: requests (>=2.31.0,<3.0.0)
Project-URL: Homepage, https://github.com/salah55s/beehiiv-python-client
Project-URL: Repository, https://github.com/salah55s/beehiiv-python-client
